registrations
