Metadata-Version: 1.0
Name: fh-django-registrations
Version: 0.1.3
Summary: A Django app to provide account verification to activate and allow registering via email or SMS.
Home-page: http://www.futurehaus.com/
Author: UNKNOWN
Author-email: UNKNOWN
License: UNKNOWN
Platform: UNKNOWN
